anfrss/__init__.py
anfrss/__main__.py
anfrss/assets/anf.png
anfrss/gui/__init__.py
anfrss/gui/guiapp.py
anfrss/parser/__init__.py
anfrss/parser/anffeed.py
tests/__init__.py
tests/test_anffeed.py
ANF_Feed-0.0.2.3.dist-info/LICENSE
ANF_Feed-0.0.2.3.dist-info/METADATA
ANF_Feed-0.0.2.3.dist-info/WHEEL
ANF_Feed-0.0.2.3.dist-info/entry_points.txt
ANF_Feed-0.0.2.3.dist-info/top_level.txt
ANF_Feed-0.0.2.3.dist-info/RECORD
