Metadata-Version: 2.1
Name: ANF-Feed
Version: 0.0.2.3
Summary: Read ANF Feeds
Home-page: https://github.com/m1ghtfr3e/ANF-Feed-Reader
Author: m1ghtfr3e
License: GPLv3
Project-URL: Source, https://github.com/m1ghtfr3e/ANF-Feed-Reader
Project-URL: Bug Reports, https://github.com/m1ghtfr3e/ANF-Feed-Reader/issues
Project-URL: PyPi Project Site, https://pypi.org/project/ANF-Feed/
Keywords: anf,feed,rss,rojava
Platform: UNKNOWN
Classifier: Programming Language :: Python :: 3
Classifier: Development Status :: 3 - Alpha
Classifier: License :: OSI Approved :: GNU General Public License v3 (GPLv3)
Classifier: Environment :: X11 Applications :: Qt
Classifier: Intended Audience :: Other Audience
Classifier: Natural Language :: English
Classifier: Topic :: Internet :: WWW/HTTP :: Dynamic Content :: News/Diary
Requires-Python: >=3
Requires-Dist: feedparser
Requires-Dist: requests
Requires-Dist: PyQt5
Requires-Dist: qdarkstyle
